[
  {
    "id": "1",
    "first_name": "Margaret",
    "last_name": "Brooks",
    "email": "mbrooks0@intel.com"
  }, {
    "id": "2",
    "first_name": "Emily",
    "last_name": "Schmidt",
    "email": "eschmidt1@mac.com"
  }, {
    "id": "3",
    "first_name": "Ernest",
    "last_name": "Banks",
    "email": "ebanks2@storify.com"
  }, {
    "id": "4",
    "first_name": "Shirley",
    "last_name": "Pierce",
    "email": "spierce3@sfgate.com"
  }, {
    "id": "5",
    "first_name": "Theresa",
    "last_name": "Nichols",
    "email": "tnichols4@bluehost.com"
  }, {
    "id": "6",
    "first_name": "Pamela",
    "last_name": "Jackson",
    "email": "pjackson5@xrea.com"
  }, {
    "id": "7",
    "first_name": "Howard",
    "last_name": "Ford",
    "email": "hford6@facebook.com"
  }, {
    "id": "8",
    "first_name": "Eric",
    "last_name": "Simmons",
    "email": "esimmons7@google.ca"
  }, {
    "id": "9",
    "first_name": "Diane",
    "last_name": "Harper",
    "email": "dharper8@whitehouse.gov"
  }, {
    "id": "10",
    "first_name": "Antonio",
    "last_name": "Sullivan",
    "email": "asullivan9@cnbc.com"
  }, {
    "id": "11",
    "first_name": "Elizabeth",
    "last_name": "Burke",
    "email": "eburkea@boston.com"
  }, {
    "id": "12",
    "first_name": "Paul",
    "last_name": "Scott",
    "email": "pscottb@weibo.com"
  }, {
    "id": "13",
    "first_name": "Wayne",
    "last_name": "Davis",
    "email": "wdavisc@nbcnews.com"
  }, {
    "id": "14",
    "first_name": "Cheryl",
    "last_name": "Thomas",
    "email": "cthomasd@buzzfeed.com"
  }, {
    "id": "15",
    "first_name": "Adam",
    "last_name": "Dean",
    "email": "adeane@blogs.com"
  }, {
    "id": "16",
    "first_name": "Mark",
    "last_name": "Bowman",
    "email": "mbowmanf@aboutads.info"
  }, {
    "id": "17",
    "first_name": "Cynthia",
    "last_name": "Jordan",
    "email": "cjordang@unc.edu"
  }, {
    "id": "18",
    "first_name": "Bruce",
    "last_name": "Anderson",
    "email": "bandersonh@youku.com"
  }, {
    "id": "19",
    "first_name": "Wanda",
    "last_name": "Reynolds",
    "email": "wreynoldsi@dropbox.com"
  }, {
    "id": "20",
    "first_name": "Lois",
    "last_name": "Gardner",
    "email": "lgardnerj@eepurl.com"
  }, {
    "id": "21",
    "first_name": "Scott",
    "last_name": "Mendoza",
    "email": "smendozak@blog.com"
  }, {
    "id": "22",
    "first_name": "Diane",
    "last_name": "Davis",
    "email": "ddavisl@cocolog-nifty.com"
  }, {
    "id": "23",
    "first_name": "Kathleen",
    "last_name": "Wood",
    "email": "kwoodm@ihg.com"
  }, {
    "id": "24",
    "first_name": "Robin",
    "last_name": "Stewart",
    "email": "rstewartn@mail.ru"
  }, {
    "id": "25",
    "first_name": "Maria",
    "last_name": "Hamilton",
    "email": "mhamiltono@omniture.com"
  }
]
